Metadata-Version: 2.1
Name: HousePredicition
Version: 0.0.1
Summary: House Predicition Notebook
Home-page: http://pypi.python.org/pypi/HousePredicition/
Author: Sahil Jaswal
Author-email: sj89808@gmail.com
License: MIT
Keywords: prediction
Platform: UNKNOWN
Classifier: Development Status :: 5 - Production/Stable
Classifier: Intended Audience :: Education
Classifier: Operating System :: Microsoft :: Windows :: Windows 10
Classifier: License :: OSI Approved :: MIT License
Classifier: Programming Language :: Python :: 3
License-File: LICENSE.txt
